[{"faceAnnotations":[],"landmarkAnnotations":[],"logoAnnotations":[],"labelAnnotations":[],"textAnnotations":[{"locations":[],"properties":[],"mid":"","locale":"et","description":"ほんとに\nあった!\n果\ntulistit hotel\nEN\nSIE\n生\n先\n19\n松本ひで吉\nCOMICS\n","score":0,"confidence":0,"topicality":0,"boundingPoly":{"vertices":[{"x":64,"y":41},{"x":956,"y":41},{"x":956,"y":1501},{"x":64,"y":1501}],"normalizedVertices":[]}},{"locations":[],"properties":[],"mid":"","locale":"","description":"ほんとに","score":0,"confidence":0,"topicality":0,"boundingPoly":{"vertices":[{"x":75,"y":43},{"x":326,"y":41},{"x":327,"y":113},{"x":76,"y":115}],"normalizedVertices":[]}},{"locations":[],"properties":[],"mid":"","locale":"","description":"あっ","score":0,"confidence":0,"topicality":0,"boundingPoly":{"vertices":[{"x":556,"y":44},{"x":688,"y":44},{"x":688,"y":119},{"x":556,"y":119}],"normalizedVertices":[]}},{"locations":[],"properties":[],"mid":"","locale":"","description":"た","score":0,"confidence":0,"topicality":0,"boundingPoly":{"vertices":[{"x":726,"y":44},{"x":745,"y":44},{"x":745,"y":119},{"x":726,"y":119}],"normalizedVertices":[]}},{"locations":[],"properties":[],"mid":"","locale":"","description":"!","score":0,"confidence":0,"topicality":0,"boundingPoly":{"vertices":[{"x":768,"y":44},{"x":787,"y":44},{"x":787,"y":119},{"x":768,"y":119}],"normalizedVertices":[]}},{"locations":[],"properties":[],"mid":"","locale":"","description":"果","score":0,"confidence":0,"topicality":0,"boundingPoly":{"vertices":[{"x":436,"y":77},{"x":487,"y":73},{"x":500,"y":246},{"x":449,"y":249}],"normalizedVertices":[]}},{"locations":[],"properties":[],"mid":"","locale":"","description":"tulistit","score":0,"confidence":0,"topicality":0,"boundingPoly":{"vertices":[{"x":613,"y":153},{"x":722,"y":167},{"x":714,"y":232},{"x":605,"y":218}],"normalizedVertices":[]}},{"locations":[],"properties":[],"mid":"","locale":"","description":"hotel","score":0,"confidence":0,"topicality":0,"boundingPoly":{"vertices":[{"x":729,"y":168},{"x":777,"y":174},{"x":768,"y":239},{"x":721,"y":232}],"normalizedVertices":[]}},{"locations":[],"properties":[],"mid":"","locale":"","description":"EN","score":0,"confidence":0,"topicality":0,"boundingPoly":{"vertices":[{"x":110,"y":188},{"x":301,"y":186},{"x":302,"y":275},{"x":111,"y":277}],"normalizedVertices":[]}},{"locations":[],"properties":[],"mid":"","locale":"","description":"SIE","score":0,"confidence":0,"topicality":0,"boundingPoly":{"vertices":[{"x":64,"y":295},{"x":342,"y":289},{"x":344,"y":389},{"x":66,"y":395}],"normalizedVertices":[]}},{"locations":[],"properties":[],"mid":"","locale":"","description":"生","score":0,"confidence":0,"topicality":0,"boundingPoly":{"vertices":[{"x":896,"y":147},{"x":951,"y":147},{"x":953,"y":334},{"x":898,"y":334}],"normalizedVertices":[]}},{"locations":[],"properties":[],"mid":"","locale":"","description":"先","score":0,"confidence":0,"topicality":0,"boundingPoly":{"vertices":[{"x":667,"y":255},{"x":726,"y":256},{"x":724,"y":457},{"x":665,"y":456}],"normalizedVertices":[]}},{"locations":[],"properties":[],"mid":"","locale":"","description":"19","score":0,"confidence":0,"topicality":0,"boundingPoly":{"vertices":[{"x":833,"y":490},{"x":946,"y":484},{"x":956,"y":689},{"x":843,"y":695}],"normalizedVertices":[]}},{"locations":[],"properties":[],"mid":"","locale":"","description":"松本","score":0,"confidence":0,"topicality":0,"boundingPoly":{"vertices":[{"x":365,"y":1359},{"x":504,"y":1358},{"x":505,"y":1444},{"x":366,"y":1445}],"normalizedVertices":[]}},{"locations":[],"properties":[],"mid":"","locale":"","description":"ひで吉","score":0,"confidence":0,"topicality":0,"boundingPoly":{"vertices":[{"x":509,"y":1358},{"x":714,"y":1356},{"x":715,"y":1442},{"x":510,"y":1444}],"normalizedVertices":[]}},{"locations":[],"properties":[],"mid":"","locale":"","description":"COMICS","score":0,"confidence":0,"topicality":0,"boundingPoly":{"vertices":[{"x":471,"y":1480},{"x":572,"y":1480},{"x":572,"y":1501},{"x":471,"y":1501}],"normalizedVertices":[]}}],"localizedObjectAnnotations":[],"safeSearchAnnotation":null,"imagePropertiesAnnotation":null,"error":null,"cropHintsAnnotation":null,"fullTextAnnotation":{"pages":[{"blocks":[{"paragraphs":[{"words":[{"symbols":[{"property":null,"boundingBox":{"vertices":[{"x":75,"y":43},{"x":144,"y":42},{"x":145,"y":113},{"x":76,"y":114}],"normalizedVertices":[]},"text":"ほ","confidence":0.9800000190734863},{"property":null,"boundingBox":{"vertices":[{"x":167,"y":43},{"x":205,"y":43},{"x":206,"y":114},{"x":168,"y":114}],"normalizedVertices":[]},"text":"ん","confidence":0.9900000095367432},{"property":null,"boundingBox":{"vertices":[{"x":214,"y":42},{"x":255,"y":42},{"x":256,"y":113},{"x":215,"y":113}],"normalizedVertices":[]},"text":"と","confidence":0.9900000095367432},{"property":{"detectedLanguages":[],"detectedBreak":{"type":"LINE_BREAK","isPrefix":false}},"boundingBox":{"vertices":[{"x":282,"y":42},{"x":326,"y":42},{"x":327,"y":113},{"x":283,"y":113}],"normalizedVertices":[]},"text":"に","confidence":0.949999988079071}],"property":null,"boundingBox":{"vertices":[{"x":75,"y":43},{"x":326,"y":41},{"x":327,"y":113},{"x":76,"y":115}],"normalizedVertices":[]},"confidence":0.9700000286102295}],"property":null,"boundingBox":{"vertices":[{"x":75,"y":43},{"x":326,"y":41},{"x":327,"y":113},{"x":76,"y":115}],"normalizedVertices":[]},"confidence":0.9700000286102295}],"property":null,"boundingBox":{"vertices":[{"x":75,"y":43},{"x":326,"y":41},{"x":327,"y":113},{"x":76,"y":115}],"normalizedVertices":[]},"blockType":"TEXT","confidence":0.9700000286102295},{"paragraphs":[{"words":[{"symbols":[{"property":null,"boundingBox":{"vertices":[{"x":556,"y":44},{"x":637,"y":44},{"x":637,"y":119},{"x":556,"y":119}],"normalizedVertices":[]},"text":"あ","confidence":0.9800000190734863},{"property":null,"boundingBox":{"vertices":[{"x":658,"y":44},{"x":688,"y":44},{"x":688,"y":119},{"x":658,"y":119}],"normalizedVertices":[]},"text":"っ","confidence":0.9900000095367432}],"property":null,"boundingBox":{"vertices":[{"x":556,"y":44},{"x":688,"y":44},{"x":688,"y":119},{"x":556,"y":119}],"normalizedVertices":[]},"confidence":0.9800000190734863},{"symbols":[{"property":null,"boundingBox":{"vertices":[{"x":726,"y":44},{"x":745,"y":44},{"x":745,"y":119},{"x":726,"y":119}],"normalizedVertices":[]},"text":"た","confidence":0.9900000095367432}],"property":null,"boundingBox":{"vertices":[{"x":726,"y":44},{"x":745,"y":44},{"x":745,"y":119},{"x":726,"y":119}],"normalizedVertices":[]},"confidence":0.9900000095367432},{"symbols":[{"property":{"detectedLanguages":[],"detectedBreak":{"type":"LINE_BREAK","isPrefix":false}},"boundingBox":{"vertices":[{"x":768,"y":44},{"x":787,"y":44},{"x":787,"y":119},{"x":768,"y":119}],"normalizedVertices":[]},"text":"!","confidence":0.17000000178813934}],"property":null,"boundingBox":{"vertices":[{"x":768,"y":44},{"x":787,"y":44},{"x":787,"y":119},{"x":768,"y":119}],"normalizedVertices":[]},"confidence":0.17000000178813934}],"property":null,"boundingBox":{"vertices":[{"x":556,"y":44},{"x":787,"y":44},{"x":787,"y":119},{"x":556,"y":119}],"normalizedVertices":[]},"confidence":0.7799999713897705}],"property":null,"boundingBox":{"vertices":[{"x":556,"y":44},{"x":787,"y":44},{"x":787,"y":119},{"x":556,"y":119}],"normalizedVertices":[]},"blockType":"TEXT","confidence":0.7799999713897705},{"paragraphs":[{"words":[{"symbols":[{"property":{"detectedLanguages":[],"detectedBreak":{"type":"LINE_BREAK","isPrefix":false}},"boundingBox":{"vertices":[{"x":436,"y":77},{"x":487,"y":73},{"x":500,"y":246},{"x":449,"y":249}],"normalizedVertices":[]},"text":"果","confidence":0.6299999952316284}],"property":null,"boundingBox":{"vertices":[{"x":436,"y":77},{"x":487,"y":73},{"x":500,"y":246},{"x":449,"y":249}],"normalizedVertices":[]},"confidence":0.6299999952316284}],"property":null,"boundingBox":{"vertices":[{"x":436,"y":77},{"x":487,"y":73},{"x":500,"y":246},{"x":449,"y":249}],"normalizedVertices":[]},"confidence":0.6299999952316284}],"property":null,"boundingBox":{"vertices":[{"x":436,"y":77},{"x":487,"y":73},{"x":500,"y":246},{"x":449,"y":249}],"normalizedVertices":[]},"blockType":"TEXT","confidence":0.6299999952316284},{"paragraphs":[{"words":[{"symbols":[{"property":{"detectedLanguages":[{"languageCode":"et","confidence":0}],"detectedBreak":null},"boundingBox":{"vertices":[{"x":613,"y":153},{"x":629,"y":155},{"x":621,"y":219},{"x":605,"y":217}],"normalizedVertices":[]},"text":"t","confidence":0.3199999928474426},{"property":{"detectedLanguages":[{"languageCode":"et","confidence":0}],"detectedBreak":null},"boundingBox":{"vertices":[{"x":633,"y":156},{"x":646,"y":158},{"x":638,"y":222},{"x":625,"y":220}],"normalizedVertices":[]},"text":"u","confidence":0.5400000214576721},{"property":{"detectedLanguages":[{"languageCode":"et","confidence":0}],"detectedBreak":null},"boundingBox":{"vertices":[{"x":649,"y":158},{"x":658,"y":159},{"x":650,"y":224},{"x":641,"y":222}],"normalizedVertices":[]},"text":"l","confidence":0.5899999737739563},{"property":{"detectedLanguages":[{"languageCode":"et","confidence":0}],"detectedBreak":null},"boundingBox":{"vertices":[{"x":658,"y":159},{"x":663,"y":160},{"x":655,"y":224},{"x":650,"y":223}],"normalizedVertices":[]},"text":"i","confidence":0.75},{"property":{"detectedLanguages":[{"languageCode":"et","confidence":0}],"detectedBreak":null},"boundingBox":{"vertices":[{"x":662,"y":160},{"x":667,"y":161},{"x":659,"y":225},{"x":654,"y":224}],"normalizedVertices":[]},"text":"s","confidence":0.4399999976158142},{"property":{"detectedLanguages":[{"languageCode":"et","confidence":0}],"detectedBreak":null},"boundingBox":{"vertices":[{"x":668,"y":161},{"x":687,"y":163},{"x":679,"y":228},{"x":660,"y":225}],"normalizedVertices":[]},"text":"t","confidence":0.14000000059604645},{"property":{"detectedLanguages":[{"languageCode":"et","confidence":0}],"detectedBreak":null},"boundingBox":{"vertices":[{"x":689,"y":163},{"x":696,"y":164},{"x":688,"y":228},{"x":681,"y":227}],"normalizedVertices":[]},"text":"i","confidence":0.41999998688697815},{"property":{"detectedLanguages":[{"languageCode":"et","confidence":0}],"detectedBreak":{"type":"SPACE","isPrefix":false}},"boundingBox":{"vertices":[{"x":697,"y":164},{"x":722,"y":167},{"x":714,"y":232},{"x":689,"y":228}],"normalizedVertices":[]},"text":"t","confidence":0.11999999731779099}],"property":{"detectedLanguages":[{"languageCode":"et","confidence":0}],"detectedBreak":null},"boundingBox":{"vertices":[{"x":613,"y":153},{"x":722,"y":167},{"x":714,"y":232},{"x":605,"y":218}],"normalizedVertices":[]},"confidence":0.4099999964237213},{"symbols":[{"property":{"detectedLanguages":[{"languageCode":"et","confidence":0}],"detectedBreak":null},"boundingBox":{"vertices":[{"x":729,"y":168},{"x":734,"y":169},{"x":726,"y":233},{"x":721,"y":232}],"normalizedVertices":[]},"text":"h","confidence":0.699999988079071},{"property":{"detectedLanguages":[{"languageCode":"et","confidence":0}],"detectedBreak":null},"boundingBox":{"vertices":[{"x":734,"y":169},{"x":741,"y":170},{"x":733,"y":234},{"x":726,"y":233}],"normalizedVertices":[]},"text":"o","confidence":0.4000000059604645},{"property":{"detectedLanguages":[{"languageCode":"et","confidence":0}],"detectedBreak":null},"boundingBox":{"vertices":[{"x":742,"y":170},{"x":753,"y":171},{"x":745,"y":236},{"x":734,"y":234}],"normalizedVertices":[]},"text":"t","confidence":0.8500000238418579},{"property":{"detectedLanguages":[{"languageCode":"et","confidence":0}],"detectedBreak":null},"boundingBox":{"vertices":[{"x":754,"y":171},{"x":762,"y":172},{"x":754,"y":236},{"x":746,"y":235}],"normalizedVertices":[]},"text":"e","confidence":0.28999999165534973},{"property":{"detectedLanguages":[{"languageCode":"et","confidence":0}],"detectedBreak":{"type":"LINE_BREAK","isPrefix":false}},"boundingBox":{"vertices":[{"x":766,"y":173},{"x":777,"y":174},{"x":769,"y":239},{"x":758,"y":237}],"normalizedVertices":[]},"text":"l","confidence":0.09000000357627869}],"property":{"detectedLanguages":[{"languageCode":"et","confidence":0}],"detectedBreak":null},"boundingBox":{"vertices":[{"x":729,"y":168},{"x":777,"y":174},{"x":768,"y":239},{"x":721,"y":232}],"normalizedVertices":[]},"confidence":0.46000000834465027}],"property":{"detectedLanguages":[{"languageCode":"et","confidence":1}],"detectedBreak":null},"boundingBox":{"vertices":[{"x":613,"y":153},{"x":777,"y":174},{"x":768,"y":239},{"x":605,"y":218}],"normalizedVertices":[]},"confidence":0.4300000071525574}],"property":{"detectedLanguages":[{"languageCode":"et","confidence":1}],"detectedBreak":null},"boundingBox":{"vertices":[{"x":613,"y":153},{"x":777,"y":174},{"x":768,"y":239},{"x":605,"y":218}],"normalizedVertices":[]},"blockType":"TEXT","confidence":0.4300000071525574},{"paragraphs":[{"words":[{"symbols":[{"property":null,"boundingBox":{"vertices":[{"x":110,"y":188},{"x":171,"y":187},{"x":172,"y":276},{"x":111,"y":277}],"normalizedVertices":[]},"text":"E","confidence":0.7300000190734863},{"property":{"detectedLanguages":[],"detectedBreak":{"type":"EOL_SURE_SPACE","isPrefix":false}},"boundingBox":{"vertices":[{"x":174,"y":187},{"x":301,"y":186},{"x":302,"y":275},{"x":175,"y":276}],"normalizedVertices":[]},"text":"N","confidence":0.1599999964237213}],"property":null,"boundingBox":{"vertices":[{"x":110,"y":188},{"x":301,"y":186},{"x":302,"y":275},{"x":111,"y":277}],"normalizedVertices":[]},"confidence":0.4399999976158142},{"symbols":[{"property":null,"boundingBox":{"vertices":[{"x":64,"y":296},{"x":135,"y":295},{"x":137,"y":394},{"x":66,"y":395}],"normalizedVertices":[]},"text":"S","confidence":0.9900000095367432},{"property":null,"boundingBox":{"vertices":[{"x":175,"y":293},{"x":194,"y":293},{"x":196,"y":392},{"x":177,"y":392}],"normalizedVertices":[]},"text":"I","confidence":0.8399999737739563},{"property":{"detectedLanguages":[],"detectedBreak":{"type":"LINE_BREAK","isPrefix":false}},"boundingBox":{"vertices":[{"x":235,"y":292},{"x":342,"y":290},{"x":344,"y":389},{"x":237,"y":391}],"normalizedVertices":[]},"text":"E","confidence":0.20999999344348907}],"property":null,"boundingBox":{"vertices":[{"x":64,"y":295},{"x":342,"y":289},{"x":344,"y":389},{"x":66,"y":395}],"normalizedVertices":[]},"confidence":0.6800000071525574}],"property":null,"boundingBox":{"vertices":[{"x":62,"y":189},{"x":340,"y":185},{"x":343,"y":391},{"x":65,"y":395}],"normalizedVertices":[]},"confidence":0.5799999833106995}],"property":null,"boundingBox":{"vertices":[{"x":62,"y":189},{"x":340,"y":185},{"x":343,"y":391},{"x":65,"y":395}],"normalizedVertices":[]},"blockType":"TEXT","confidence":0.5799999833106995},{"paragraphs":[{"words":[{"symbols":[{"property":{"detectedLanguages":[],"detectedBreak":{"type":"LINE_BREAK","isPrefix":false}},"boundingBox":{"vertices":[{"x":896,"y":147},{"x":951,"y":147},{"x":953,"y":334},{"x":898,"y":334}],"normalizedVertices":[]},"text":"生","confidence":0.9200000166893005}],"property":null,"boundingBox":{"vertices":[{"x":896,"y":147},{"x":951,"y":147},{"x":953,"y":334},{"x":898,"y":334}],"normalizedVertices":[]},"confidence":0.9200000166893005}],"property":null,"boundingBox":{"vertices":[{"x":896,"y":147},{"x":951,"y":147},{"x":953,"y":334},{"x":898,"y":334}],"normalizedVertices":[]},"confidence":0.9200000166893005}],"property":null,"boundingBox":{"vertices":[{"x":896,"y":147},{"x":951,"y":147},{"x":953,"y":334},{"x":898,"y":334}],"normalizedVertices":[]},"blockType":"TEXT","confidence":0.9200000166893005},{"paragraphs":[{"words":[{"symbols":[{"property":{"detectedLanguages":[],"detectedBreak":{"type":"LINE_BREAK","isPrefix":false}},"boundingBox":{"vertices":[{"x":667,"y":255},{"x":726,"y":256},{"x":724,"y":457},{"x":665,"y":456}],"normalizedVertices":[]},"text":"先","confidence":0.6399999856948853}],"property":null,"boundingBox":{"vertices":[{"x":667,"y":255},{"x":726,"y":256},{"x":724,"y":457},{"x":665,"y":456}],"normalizedVertices":[]},"confidence":0.6399999856948853}],"property":null,"boundingBox":{"vertices":[{"x":667,"y":255},{"x":726,"y":256},{"x":724,"y":457},{"x":665,"y":456}],"normalizedVertices":[]},"confidence":0.6399999856948853}],"property":null,"boundingBox":{"vertices":[{"x":667,"y":255},{"x":726,"y":256},{"x":724,"y":457},{"x":665,"y":456}],"normalizedVertices":[]},"blockType":"TEXT","confidence":0.6399999856948853},{"paragraphs":[{"words":[{"symbols":[{"property":null,"boundingBox":{"vertices":[{"x":833,"y":490},{"x":886,"y":487},{"x":896,"y":692},{"x":843,"y":695}],"normalizedVertices":[]},"text":"1","confidence":0.9900000095367432},{"property":{"detectedLanguages":[],"detectedBreak":{"type":"LINE_BREAK","isPrefix":false}},"boundingBox":{"vertices":[{"x":895,"y":487},{"x":946,"y":484},{"x":956,"y":689},{"x":905,"y":692}],"normalizedVertices":[]},"text":"9","confidence":0.9900000095367432}],"property":null,"boundingBox":{"vertices":[{"x":833,"y":490},{"x":946,"y":484},{"x":956,"y":689},{"x":843,"y":695}],"normalizedVertices":[]},"confidence":0.9900000095367432}],"property":null,"boundingBox":{"vertices":[{"x":833,"y":490},{"x":946,"y":484},{"x":956,"y":689},{"x":843,"y":695}],"normalizedVertices":[]},"confidence":0.9900000095367432}],"property":null,"boundingBox":{"vertices":[{"x":833,"y":490},{"x":946,"y":484},{"x":956,"y":689},{"x":843,"y":695}],"normalizedVertices":[]},"blockType":"TEXT","confidence":0.9900000095367432},{"paragraphs":[{"words":[{"symbols":[{"property":{"detectedLanguages":[{"languageCode":"ja","confidence":0}],"detectedBreak":null},"boundingBox":{"vertices":[{"x":365,"y":1359},{"x":434,"y":1358},{"x":435,"y":1443},{"x":366,"y":1444}],"normalizedVertices":[]},"text":"松","confidence":0.9900000095367432},{"property":{"detectedLanguages":[{"languageCode":"ja","confidence":0}],"detectedBreak":null},"boundingBox":{"vertices":[{"x":437,"y":1359},{"x":504,"y":1358},{"x":505,"y":1443},{"x":438,"y":1444}],"normalizedVertices":[]},"text":"本","confidence":0.9900000095367432}],"property":{"detectedLanguages":[{"languageCode":"ja","confidence":0}],"detectedBreak":null},"boundingBox":{"vertices":[{"x":365,"y":1359},{"x":504,"y":1358},{"x":505,"y":1444},{"x":366,"y":1445}],"normalizedVertices":[]},"confidence":0.9900000095367432},{"symbols":[{"property":{"detectedLanguages":[{"languageCode":"ja","confidence":0}],"detectedBreak":null},"boundingBox":{"vertices":[{"x":509,"y":1358},{"x":572,"y":1358},{"x":573,"y":1443},{"x":510,"y":1443}],"normalizedVertices":[]},"text":"ひ","confidence":0.9900000095367432},{"property":{"detectedLanguages":[{"languageCode":"ja","confidence":0}],"detectedBreak":null},"boundingBox":{"vertices":[{"x":579,"y":1358},{"x":642,"y":1358},{"x":643,"y":1443},{"x":580,"y":1443}],"normalizedVertices":[]},"text":"で","confidence":0.9900000095367432},{"property":{"detectedLanguages":[{"languageCode":"ja","confidence":0}],"detectedBreak":{"type":"LINE_BREAK","isPrefix":false}},"boundingBox":{"vertices":[{"x":647,"y":1357},{"x":714,"y":1356},{"x":715,"y":1441},{"x":648,"y":1442}],"normalizedVertices":[]},"text":"吉","confidence":0.9900000095367432}],"property":{"detectedLanguages":[{"languageCode":"ja","confidence":0}],"detectedBreak":null},"boundingBox":{"vertices":[{"x":509,"y":1358},{"x":714,"y":1356},{"x":715,"y":1442},{"x":510,"y":1444}],"normalizedVertices":[]},"confidence":0.9900000095367432}],"property":{"detectedLanguages":[{"languageCode":"ja","confidence":1}],"detectedBreak":null},"boundingBox":{"vertices":[{"x":365,"y":1359},{"x":714,"y":1356},{"x":715,"y":1442},{"x":366,"y":1445}],"normalizedVertices":[]},"confidence":0.9900000095367432}],"property":{"detectedLanguages":[{"languageCode":"ja","confidence":1}],"detectedBreak":null},"boundingBox":{"vertices":[{"x":365,"y":1359},{"x":714,"y":1356},{"x":715,"y":1442},{"x":366,"y":1445}],"normalizedVertices":[]},"blockType":"TEXT","confidence":0.9900000095367432},{"paragraphs":[{"words":[{"symbols":[{"property":{"detectedLanguages":[{"languageCode":"en","confidence":0}],"detectedBreak":null},"boundingBox":{"vertices":[{"x":471,"y":1480},{"x":488,"y":1480},{"x":488,"y":1501},{"x":471,"y":1501}],"normalizedVertices":[]},"text":"C","confidence":0.9900000095367432},{"property":{"detectedLanguages":[{"languageCode":"en","confidence":0}],"detectedBreak":null},"boundingBox":{"vertices":[{"x":492,"y":1480},{"x":503,"y":1480},{"x":503,"y":1501},{"x":492,"y":1501}],"normalizedVertices":[]},"text":"O","confidence":0.9900000095367432},{"property":{"detectedLanguages":[{"languageCode":"en","confidence":0}],"detectedBreak":null},"boundingBox":{"vertices":[{"x":509,"y":1480},{"x":522,"y":1480},{"x":522,"y":1501},{"x":509,"y":1501}],"normalizedVertices":[]},"text":"M","confidence":1},{"property":{"detectedLanguages":[{"languageCode":"en","confidence":0}],"detectedBreak":null},"boundingBox":{"vertices":[{"x":531,"y":1480},{"x":540,"y":1480},{"x":540,"y":1501},{"x":531,"y":1501}],"normalizedVertices":[]},"text":"I","confidence":0.9900000095367432},{"property":{"detectedLanguages":[{"languageCode":"en","confidence":0}],"detectedBreak":null},"boundingBox":{"vertices":[{"x":541,"y":1480},{"x":548,"y":1480},{"x":548,"y":1501},{"x":541,"y":1501}],"normalizedVertices":[]},"text":"C","confidence":0.9900000095367432},{"property":{"detectedLanguages":[{"languageCode":"en","confidence":0}],"detectedBreak":{"type":"LINE_BREAK","isPrefix":false}},"boundingBox":{"vertices":[{"x":554,"y":1480},{"x":572,"y":1480},{"x":572,"y":1501},{"x":554,"y":1501}],"normalizedVertices":[]},"text":"S","confidence":0.9900000095367432}],"property":{"detectedLanguages":[{"languageCode":"en","confidence":0}],"detectedBreak":null},"boundingBox":{"vertices":[{"x":471,"y":1480},{"x":572,"y":1480},{"x":572,"y":1501},{"x":471,"y":1501}],"normalizedVertices":[]},"confidence":0.9900000095367432}],"property":{"detectedLanguages":[{"languageCode":"en","confidence":1}],"detectedBreak":null},"boundingBox":{"vertices":[{"x":471,"y":1480},{"x":572,"y":1480},{"x":572,"y":1501},{"x":471,"y":1501}],"normalizedVertices":[]},"confidence":0.9900000095367432}],"property":{"detectedLanguages":[{"languageCode":"en","confidence":1}],"detectedBreak":null},"boundingBox":{"vertices":[{"x":471,"y":1480},{"x":572,"y":1480},{"x":572,"y":1501},{"x":471,"y":1501}],"normalizedVertices":[]},"blockType":"TEXT","confidence":0.9900000095367432}],"property":{"detectedLanguages":[{"languageCode":"et","confidence":0.3100000023841858},{"languageCode":"en","confidence":0.14000000059604645},{"languageCode":"ja","confidence":0.11999999731779099}],"detectedBreak":null},"width":1078,"height":1600,"confidence":0}],"text":"ほんとに\nあった!\n果\ntulistit hotel\nEN\nSIE\n生\n先\n19\n松本ひで吉\nCOMICS\n"},"webDetection":null,"productSearchResults":null,"context":null}]